{"id":227724,"name":"名探偵コナン ゼロの執行人","name_cn":"名侦探柯南 零的执行人","type":"动画","image":"b9/26/227724_o3cmo.jpg","link":"https://bgm.tv/subject/227724","eps":1,"collection":{"on_hold":20,"dropped":25,"wish":162,"collect":2763,"doing":10},"date":"2018-04-13","summary":"作为东京峰会召开地的东京湾新设施“海洋边缘”。在峰会召开的5月1日有约2万名警察出动的这一超巨大设施，发生了大规模爆炸案！那里，有隶属于暗中掌控全国公安警察、俗称为“零”的警察厅秘密组织的安室透的身影。秘密暗中出动的安室的神秘行动令柯南不禁感到蹊跷。\r\n根据现场留下的作为证据的指纹，犯人被断定为曾在警视厅就职的毛利小五郎！与安室围绕小五郎的逮捕开始敌对的柯南听说了过去安室曾将嫌疑人逼至自杀的奇妙案件。随后在决定起诉小五郎的那时，在戒备森严的东京都内，同时爆发了多起难以理解的恐袭！\r\n柯南和公安警察正接近着隐藏在案件后的阴谋，峰会召开那天也被确定是大型无人探测器“天鹅”完成在火星的任务返回地球的日子。究竟，迫近的X日会发生什么？神秘的存在——安室透，究竟是敌人，还是伙伴？","rating":{"rank":6994,"total":1679,"count":{"1":11,"2":12,"3":34,"4":152,"5":338,"6":683,"7":337,"8":84,"9":13,"10":15},"score":5.9},"updated_at":"2023-10-21T21:35:45+08:00"}